{
  "kind": "collectionType",
  "collectionName": "items",
  "info": {
    "singularName": "item",
    "pluralName": "items",
    "displayName": "Items"
  },
  "options": {
    "draftAndPublish": false
  },
  "pluginOptions": {},
  "attributes": {
    "product": {
      "type": "relation",
      "relation": "oneToOne",
      "target": "api::production.production"
    },
    "quantity": {
      "type": "integer"
    },
    "order": {
      "type": "relation",
      "relation": "manyToOne",
      "target": "api::order.order",
      "inversedBy": "items"
    }
  }
}
